upydev/__init__.py
upydev/argcompleter.py
upydev/bleio.py
upydev/commandlib.py
upydev/conftest.py
upydev/debugging.py
upydev/devicemanagement.py
upydev/fileio.py
upydev/firmwaretools.py
upydev/gencommands.py
upydev/groupmode.py
upydev/helpinfo.py
upydev/keygen.py
upydev/otabletool.py
upydev/otatool.py
upydev/playbook.py
upydev/pytest.ini
upydev/repls.py
upydev/sdcommands.py
upydev/serialio.py
upydev/shellrepls.py
upydev/style_customs.py
upydev/style_monokaidark.py
upydev/tableresults.py
upydev/test_dev.py
upydev/upip_host.py
upydev/websocket_helper.py
upydev/wsio.py
upydev/wss_helper_host.py
upydev/shell/__init__.py
upydev/shell/commands.py
upydev/shell/common.py
upydev/shell/constants.py
upydev/shell/keybindings.py
upydev/shell/nanoglob.py
upydev/shell/parser.py
upydev/shell/redirectsh.py
upydev/shell/shasum.py
upydev/shell/shble.py
upydev/shell/shfileio.py
upydev/shell/shfwio.py
upydev/shell/shserial.py
upydev/shell/shws.py
upydev/shell/upyconfig.py
upydev/upyutils_dir/cycles.py
upydev/upyutils_dir/nanoglob.py
upydev/upyutils_dir/shasum.py
upydev/upyutils_dir/sync_tool.py
upydev/upyutils_dir/time_it.py
upydev/upyutils_dir/uping.py
upydev/upyutils_dir/uptime.py
upydev/upyutils_dir/upylog.py
upydev/upyutils_dir/upynotify.py
upydev/upyutils_dir/upysecrets.py
upydev/upyutils_dir/upysh.py
upydev/upyutils_dir/upysh2.py
upydev/upyutils_dir/wss_helper.py
upydev/upyutils_dir/wss_repl.py
upydev-0.4.3.data/scripts/blerepl
upydev-0.4.3.data/scripts/pydfu
upydev-0.4.3.data/scripts/sh_srepl
upydev-0.4.3.data/scripts/sslweb_repl
upydev-0.4.3.data/scripts/upydev
upydev-0.4.3.data/scripts/web_repl
upydev-0.4.3.dist-info/LICENSE
upydev-0.4.3.dist-info/METADATA
upydev-0.4.3.dist-info/WHEEL
upydev-0.4.3.dist-info/top_level.txt
upydev-0.4.3.dist-info/RECORD
