Metadata-Version: 2.1
Name: upydev
Version: 0.4.3
Summary: Command line tool for MicroPython devices
Home-page: http://github.com/Carglglz/upydev
Author: Carlos Gil Gonzalez
Author-email: carlosgilglez@gmail.com
License: MIT
Classifier: Development Status :: 3 - Alpha
Classifier: Environment :: Console
Classifier: Intended Audience :: Developers
Classifier: Intended Audience :: Science/Research
Classifier: Intended Audience :: Education
Classifier: Operating System :: MacOS :: MacOS X
Classifier: Operating System :: POSIX :: Linux
Classifier: License :: OSI Approved :: MIT License
Classifier: Programming Language :: Python :: 3.6
Classifier: Programming Language :: Python :: 3.7
Classifier: Programming Language :: Python :: 3.8
Classifier: Topic :: System :: Monitoring
Classifier: Topic :: Scientific/Engineering
Classifier: Topic :: Software Development :: Embedded Systems
Classifier: Topic :: Terminals
License-File: LICENSE
Requires-Dist: websocket-client (>=1.2.3)
Requires-Dist: argcomplete (>=2.0.0)
Requires-Dist: esptool
Requires-Dist: prompt-toolkit
Requires-Dist: python-nmap
Requires-Dist: netifaces
Requires-Dist: requests
Requires-Dist: cryptography
Requires-Dist: Pygments
Requires-Dist: pyusb
Requires-Dist: packaging
Requires-Dist: upydevice (>=0.3.8)
Requires-Dist: jupyter-micropython-upydevice (>=0.0.7)
Requires-Dist: braceexpand
Requires-Dist: pyyaml
